lfm_ai_upgrade/__init__.py
lfm_ai_upgrade-5.0.1.dist-info/METADATA
lfm_ai_upgrade-5.0.1.dist-info/WHEEL
lfm_ai_upgrade-5.0.1.dist-info/top_level.txt
lfm_ai_upgrade-5.0.1.dist-info/RECORD
