Metadata-Version: 2.4
Name: lfm-ai-upgrade
Version: 5.0.1
Summary: LFM V5.0 - Critical Security Patch & Axiom Lock
Author: Keith Luton
Author-email: keith@thenewfaithchurch.org
Classifier: Programming Language :: Python :: 3
Classifier: License :: Other/Proprietary License
Classifier: Operating System :: OS Independent
Requires-Python: >=3.7
Requires-Dist: torch>=2.0.0
Requires-Dist: lfm-universal>=5.0.1
Dynamic: author
Dynamic: author-email
Dynamic: classifier
Dynamic: description
Dynamic: description-content-type
Dynamic: requires-dist
Dynamic: requires-python
Dynamic: summary
